<?xml version="1.0" encoding="UTF-8"?>
<launch4jConfig>
  <dontWrapJar>false</dontWrapJar>
  <headerType>gui</headerType>
  <jar>C:\Users\Ahmed.ElKady\Documents\NetBeansProjects\RecipeMaker_Viewer_All\dist\RecipeMaker_Viewer_All.jar</jar>
  <outfile>C:\Users\Ahmed.ElKady\Documents\NetBeansProjects\RecipeMaker_Viewer_All\dist\RECETA_VIEWER.exe</outfile>
  <errTitle>Java Not Found - Kadysoft Ltd</errTitle>
  <cmdLine></cmdLine>
  <chdir>.</chdir>
  <priority>normal</priority>
  <downloadUrl>http://java.com/download</downloadUrl>
  <supportUrl>Call Me At : +201555266002</supportUrl>
  <stayAlive>false</stayAlive>
  <restartOnCrash>true</restartOnCrash>
  <manifest></manifest>
  <icon>C:\Users\Ahmed.ElKady\Documents\NetBeansProjects\RecipeMaker_Viewer_All\recipemakericon.ico</icon>
  <jre>
    <path>Java</path>
    <bundledJre64Bit>false</bundledJre64Bit>
    <bundledJreAsFallback>false</bundledJreAsFallback>
    <minVersion></minVersion>
    <maxVersion></maxVersion>
    <jdkPreference>jdkOnly</jdkPreference>
    <runtimeBits>64</runtimeBits>
  </jre>
  <versionInfo>
    <fileVersion>3.2.1.0</fileVersion>
    <txtFileVersion>3.2.1.ks</txtFileVersion>
    <fileDescription>Recipe viewer for viewing mode only.</fileDescription>
    <copyright>All Rights Reserved @ Kadysoft Ltd. 2017 - 2024</copyright>
    <productVersion>3.2.1.0</productVersion>
    <txtProductVersion>3.2.1.ks</txtProductVersion>
    <productName>Receta</productName>
    <companyName>Kadysoft Ltd</companyName>
    <internalName>Receta</internalName>
    <originalFilename>RECETA_VIEWER.exe</originalFilename>
    <trademarks>Kadysoft Ltd.</trademarks>
    <language>ENGLISH_US</language>
  </versionInfo>
  <messages>
    <startupErr>An error occurred while starting the application.</startupErr>
    <bundledJreErr>This application was configured to use a bundled Java Runtime Environment but the runtime is missing or corrupted.</bundledJreErr>
    <jreVersionErr>This application requires a Java Runtime Environment</jreVersionErr>
    <launcherErr>The registry refers to a nonexistent Java Runtime Environment installation or the runtime is corrupted.</launcherErr>
    <instanceAlreadyExistsMsg>An application instance is already running.</instanceAlreadyExistsMsg>
  </messages>
</launch4jConfig>